{
  "response_id": "20260603_012444_460136",
  "query": "cloud-based brachytherapy treatment planning HIPAA security requirements",
  "created_at": "2026-06-03T01:24:44.460157",
  "num_sources": 1,
  "source_types": [
    "PubMed"
  ],
  "avg_confidence": 0.85,
  "verification_status": "unverified",
  "citations": [
    "[Innovations in Radiotherapy Technology.](https://pubmed.ncbi.nlm.nih.gov/27913106/)"
  ],
  "evidence": [
    {
      "evidence_id": "dcc1318ca45b",
      "claim": "PubMed ID: 27913106. 2017/02/01 00:00",
      "source_url": "https://pubmed.ncbi.nlm.nih.gov/27913106/",
      "source_type": "PubMed",
      "source_title": "Innovations in Radiotherapy Technology.",
      "accessed_at": "2026-06-03T01:24:45.975225",
      "published_at": "",
      "raw_snippet": "PubMed ID: 27913106. 2017/02/01 00:00",
      "extracted_data": {},
      "confidence": 0.85,
      "verification_status": "unverified",
      "cross_references": [],
      "search_query": "cloud-based brachytherapy treatment planning HIPAA security requirements",
      "search_type": "general",
      "cache_hit": false
    }
  ]
}