{
  "query": "HDR brachytherapy large prostate 140cc size limits guidelines",
  "timestamp": 1780459217.8815348,
  "result": {
    "success": true,
    "results": [
      {
        "title": "HDR有必要开吗？ - 知乎",
        "snippet": "一、HDR是什么 HDR是英文High Dynamic Range的缩写，意思是高动态光照渲染。 直白点讲，HDR是指一个图像中最亮处和最暗处之间的比值，能够让图像明亮的地方更亮，而黑色的地方更黑暗深邃。 …",
        "url": "https://www.zhihu.com/question/363277335",
        "source": "Bing CN"
      },
      {
        "title": "HDR（一种图像处理技术）_百度百科",
        "snippet": "2025年8月29日 · HDR（高动态范围）是一种在传统图像技术发展而成的先进图像技术。 HDR最初的概念源自CG动画，由著名显卡公司NVIDIA提出，旨在实现游戏画面中多层次的光色渲染，以获得更丰 …",
        "url": "https://baike.baidu.com/item/HDR/62027025",
        "source": "Bing CN"
      },
      {
        "title": "显示屏HDR功能？切记不要随便开！_模式_显示器_范围",
        "snippet": "2024年1月3日 · HDR模式默认是关闭的。 我们可以右击桌面选择【显示设置】，【开启】“使用HDR”，显示器会在短暂的黑屏后切换完毕。 若此处没有“使用HDR”选项， 即该显示屏不支持HDR功 …",
        "url": "https://www.sohu.com/a/749085178_100293026",
        "source": "Bing CN"
      },
      {
        "title": "免费在线屏幕HDR检测 - HDR10/Dolby Vision测试 | 视觉族",
        "snippet": "2026年5月15日 · 免费在线 HDR 检测工具。自动检测系统 HDR 支持、动态范围测试、宽色域验证。评估 DisplayHDR 等级、HDR10/Dolby Vision 能力和显示器 HDR 表现。",
        "url": "https://www.shijuezu.com/hdr-test",
        "source": "Bing CN"
      },
      {
        "title": "什么是HDR技术？HDR10、HDR400有什么区别？为什么售价 ...",
        "snippet": "2021年12月7日 · 什么是HDR？ 高动态范围图像（High-Dynamic Range，简称HDR），相比普通的图像，可以提供更多的动态范围和图像细节，根据不同的曝光时间的LDR（Low-Dynamic Range，低动 …",
        "url": "https://blog.csdn.net/lolloli/article/details/121766266",
        "source": "Bing CN"
      }
    ],
    "answer": "\nOther sources:\n- 一、HDR是什么 HDR是英文High Dynamic Range的缩写，意思是高动态光照渲染。 直白点讲，HDR是指一个图像中最亮处和最暗处之间的比值，能够让图像明亮的地方更亮，而黑色的地方更黑暗深邃。 …\n- 2025年8月29日 · HDR（高动态范围）是一种在传统图像技术发展而成的先进图像技术。 HDR最初的概念源自CG动画，由著名显卡公司NVIDIA提出，旨在实现游戏画面中多层次的光色渲染，以获得更丰 …",
    "sources": [
      "https://www.zhihu.com/question/363277335",
      "https://baike.baidu.com/item/HDR/62027025",
      "https://www.sohu.com/a/749085178_100293026",
      "https://www.shijuezu.com/hdr-test",
      "https://blog.csdn.net/lolloli/article/details/121766266"
    ],
    "evidence_chain_id": "20260603_120006_445452",
    "evidence_summary": {
      "response_id": "20260603_120006_445452",
      "query": "HDR brachytherapy large prostate 140cc size limits guidelines",
      "created_at": "2026-06-03T12:00:06.445482",
      "num_sources": 5,
      "source_types": [
        "Bing CN"
      ],
      "avg_confidence": 0.4,
      "verification_status": "unverified",
      "citations": [
        "[HDR有必要开吗？ - 知乎](https://www.zhihu.com/question/363277335)",
        "[HDR（一种图像处理技术）_百度百科](https://baike.baidu.com/item/HDR/62027025)",
        "[显示屏HDR功能？切记不要随便开！_模式_显示器_范围](https://www.sohu.com/a/749085178_100293026)",
        "[免费在线屏幕HDR检测 - HDR10/Dolby Vision测试 | 视觉族](https://www.shijuezu.com/hdr-test)",
        "[什么是HDR技术？HDR10、HDR400有什么区别？为什么售价 ...](https://blog.csdn.net/lolloli/article/details/121766266)"
      ],
      "evidence": [
        {
          "evidence_id": "a0fa5f4f1049",
          "claim": "一、HDR是什么 HDR是英文High Dynamic Range的缩写，意思是高动态光照渲染。 直白点讲，HDR是指一个图像中最亮处和最暗处之间的比值，能够让图像明亮的地方更亮，而黑色的地方更黑暗深邃。 …",
          "source_url": "https://www.zhihu.com/question/363277335",
          "source_type": "Bing CN",
          "source_title": "HDR有必要开吗？ - 知乎",
          "accessed_at": "2026-06-03T12:00:17.881085",
          "published_at": "",
          "raw_snippet": "一、HDR是什么 HDR是英文High Dynamic Range的缩写，意思是高动态光照渲染。 直白点讲，HDR是指一个图像中最亮处和最暗处之间的比值，能够让图像明亮的地方更亮，而黑色的地方更黑暗深邃。 …",
          "extracted_data": {},
          "confidence": 0.4,
          "verification_status": "unverified",
          "cross_references": [],
          "search_query": "HDR brachytherapy large prostate 140cc size limits guidelines",
          "search_type": "general",
          "cache_hit": false
        },
        {
          "evidence_id": "0d06d6c32c80",
          "claim": "2025年8月29日 · HDR（高动态范围）是一种在传统图像技术发展而成的先进图像技术。 HDR最初的概念源自CG动画，由著名显卡公司NVIDIA提出，旨在实现游戏画面中多层次的光色渲染，以获得更丰 …",
          "source_url": "https://baike.baidu.com/item/HDR/62027025",
          "source_type": "Bing CN",
          "source_title": "HDR（一种图像处理技术）_百度百科",
          "accessed_at": "2026-06-03T12:00:17.881153",
          "published_at": "",
          "raw_snippet": "2025年8月29日 · HDR（高动态范围）是一种在传统图像技术发展而成的先进图像技术。 HDR最初的概念源自CG动画，由著名显卡公司NVIDIA提出，旨在实现游戏画面中多层次的光色渲染，以获得更丰 …",
          "extracted_data": {},
          "confidence": 0.4,
          "verification_status": "unverified",
          "cross_references": [],
          "search_query": "HDR brachytherapy large prostate 140cc size limits guidelines",
          "search_type": "general",
          "cache_hit": false
        },
        {
          "evidence_id": "5d71605302c6",
          "claim": "2024年1月3日 · HDR模式默认是关闭的。 我们可以右击桌面选择【显示设置】，【开启】“使用HDR”，显示器会在短暂的黑屏后切换完毕。 若此处没有“使用HDR”选项， 即该显示屏不支持HDR功 …",
          "source_url": "https://www.sohu.com/a/749085178_100293026",
          "source_type": "Bing CN",
          "source_title": "显示屏HDR功能？切记不要随便开！_模式_显示器_范围",
          "accessed_at": "2026-06-03T12:00:17.881201",
          "published_at": "",
          "raw_snippet": "2024年1月3日 · HDR模式默认是关闭的。 我们可以右击桌面选择【显示设置】，【开启】“使用HDR”，显示器会在短暂的黑屏后切换完毕。 若此处没有“使用HDR”选项， 即该显示屏不支持HDR功 …",
          "extracted_data": {},
          "confidence": 0.4,
          "verification_status": "unverified",
          "cross_references": [],
          "search_query": "HDR brachytherapy large prostate 140cc size limits guidelines",
          "search_type": "general",
          "cache_hit": false
        },
        {
          "evidence_id": "82a78b65c6b1",
          "claim": "2026年5月15日 · 免费在线 HDR 检测工具。自动检测系统 HDR 支持、动态范围测试、宽色域验证。评估 DisplayHDR 等级、HDR10/Dolby Vision 能力和显示器 HDR 表现。",
          "source_url": "https://www.shijuezu.com/hdr-test",
          "source_type": "Bing CN",
          "source_title": "免费在线屏幕HDR检测 - HDR10/Dolby Vision测试 | 视觉族",
          "accessed_at": "2026-06-03T12:00:17.881247",
          "published_at": "",
          "raw_snippet": "2026年5月15日 · 免费在线 HDR 检测工具。自动检测系统 HDR 支持、动态范围测试、宽色域验证。评估 DisplayHDR 等级、HDR10/Dolby Vision 能力和显示器 HDR 表现。",
          "extracted_data": {},
          "confidence": 0.4,
          "verification_status": "unverified",
          "cross_references": [],
          "search_query": "HDR brachytherapy large prostate 140cc size limits guidelines",
          "search_type": "general",
          "cache_hit": false
        },
        {
          "evidence_id": "316d290f57e4",
          "claim": "2021年12月7日 · 什么是HDR？ 高动态范围图像（High-Dynamic Range，简称HDR），相比普通的图像，可以提供更多的动态范围和图像细节，根据不同的曝光时间的LDR（Low-Dynamic Range，低动 …",
          "source_url": "https://blog.csdn.net/lolloli/article/details/121766266",
          "source_type": "Bing CN",
          "source_title": "什么是HDR技术？HDR10、HDR400有什么区别？为什么售价 ...",
          "accessed_at": "2026-06-03T12:00:17.881292",
          "published_at": "",
          "raw_snippet": "2021年12月7日 · 什么是HDR？ 高动态范围图像（High-Dynamic Range，简称HDR），相比普通的图像，可以提供更多的动态范围和图像细节，根据不同的曝光时间的LDR（Low-Dynamic Range，低动 …",
          "extracted_data": {},
          "confidence": 0.4,
          "verification_status": "unverified",
          "cross_references": [],
          "search_query": "HDR brachytherapy large prostate 140cc size limits guidelines",
          "search_type": "general",
          "cache_hit": false
        }
      ]
    },
    "citations": [
      "[HDR有必要开吗？ - 知乎](https://www.zhihu.com/question/363277335)",
      "[HDR（一种图像处理技术）_百度百科](https://baike.baidu.com/item/HDR/62027025)",
      "[显示屏HDR功能？切记不要随便开！_模式_显示器_范围](https://www.sohu.com/a/749085178_100293026)",
      "[免费在线屏幕HDR检测 - HDR10/Dolby Vision测试 | 视觉族](https://www.shijuezu.com/hdr-test)",
      "[什么是HDR技术？HDR10、HDR400有什么区别？为什么售价 ...](https://blog.csdn.net/lolloli/article/details/121766266)"
    ]
  }
}